detection_datasets/__init__.py
detection_datasets/bbox.py
detection_datasets/detection_dataset.py
detection_datasets/readers/__init__.py
detection_datasets/readers/base.py
detection_datasets/readers/coco.py
detection_datasets/utils/__init__.py
detection_datasets/utils/cache.py
detection_datasets/utils/constants.py
detection_datasets/utils/factories.py
detection_datasets/utils/hub.py
detection_datasets/utils/visualization.py
detection_datasets/writers/__init__.py
detection_datasets/writers/base.py
detection_datasets/writers/coco.py
detection_datasets/writers/mmdet.py
detection_datasets/writers/yolo.py
detection_datasets-0.3.8.dist-info/METADATA
detection_datasets-0.3.8.dist-info/WHEEL
detection_datasets-0.3.8.dist-info/RECORD
