Metadata-Version: 2.1
Name: detection_datasets
Version: 0.3.8
Summary: Easily load and transform datasets for object detection
Home-page: https://github.com/blinjrm/detection-dataset
License: MIT
Author: Jerome Blin
Author-email: blinjrm@gmail.com
Requires-Python: >=3.8.1,<4.0.0
Classifier: Development Status :: 4 - Beta
Classifier: Intended Audience :: Developers
Classifier: License :: OSI Approved :: MIT License
Classifier: Programming Language :: Python :: 3
Classifier: Programming Language :: Python :: 3.9
Classifier: Programming Language :: Python :: 3.10
Classifier: Programming Language :: Python :: 3.11
Classifier: Programming Language :: Python :: 3.12
Classifier: Topic :: Software Development :: Libraries :: Python Modules
Requires-Dist: datasets[vision] (>=2.4.0,<3.0.0)
Requires-Dist: pandas (>=1.3.0,<2.0.0)
Project-URL: Repository, https://github.com/blinjrm/detection-dataset
